[
    {
        "inputs": [],
        "stateMutability": "nonpayable",
        "type": "constructor"
    },
    {
        "inputs": [
            {
                "internalType": "address",
                "name": "owner",
                "type": "address"
            }
        ],
        "name": "OwnableInvalidOwner",
        "type": "error"
    },
    {
        "inputs": [
            {
                "internalType": "address",
                "name": "account",
                "type": "address"
            }
        ],
        "name": "OwnableUnauthorizedAccount",
        "type": "error"
    },
    {
        "anonymous": false,
        "inputs": [
            {
                "indexed": true,
                "internalType": "bytes32",
                "name": "messageId",
                "type": "bytes32"
            },
            {
                "indexed": true,
                "internalType": "address",
                "name": "recipient",
                "type": "address"
            }
        ],
        "name": "MessageRetrieved",
        "type": "event"
    },
    {
        "anonymous": false,
        "inputs": [
            {
                "indexed": true,
                "internalType": "bytes32",
                "name": "messageId",
                "type": "bytes32"
            },
            {
                "indexed": true,
                "internalType": "address",
                "name": "sender",
                "type": "address"
            },
            {
                "indexed": false,
                "internalType": "string",
                "name": "ensRecipient",
                "type": "string"
            },
            {
                "indexed": false,
                "internalType": "uint256",
                "name": "unlockTime",
                "type": "uint256"
            }
        ],
        "name": "MessageStored",
        "type": "event"
    },
    {
        "anonymous": false,
        "inputs": [
            {
                "indexed": true,
                "internalType": "address",
                "name": "previousOwner",
                "type": "address"
            },
            {
                "indexed": true,
                "internalType": "address",
                "name": "newOwner",
                "type": "address"
            }
        ],
        "name": "OwnershipTransferred",
        "type": "event"
    },
    {
        "inputs": [
            {
                "internalType": "bytes32",
                "name": "",
                "type": "bytes32"
            }
        ],
        "name": "messages",
        "outputs": [
            {
                "internalType": "string",
                "name": "content",
                "type": "string"
            },
            {
                "internalType": "address",
                "name": "sender",
                "type": "address"
            },
            {
                "internalType": "string",
                "name": "ensRecipient",
                "type": "string"
            },
            {
                "internalType": "uint256",
                "name": "unlockTime",
                "type": "uint256"
            },
            {
                "internalType": "bool",
                "name": "retrieved",
                "type": "bool"
            }
        ],
        "stateMutability": "view",
        "type": "function"
    },
    {
        "inputs": [],
        "name": "owner",
        "outputs": [
            {
                "internalType": "address",
                "name": "",
                "type": "address"
            }
        ],
        "stateMutability": "view",
        "type": "function"
    },
    {
        "inputs": [],
        "name": "renounceOwnership",
        "outputs": [],
        "stateMutability": "nonpayable",
        "type": "function"
    },
    {
        "inputs": [
            {
                "internalType": "bytes32",
                "name": "_messageId",
                "type": "bytes32"
            }
        ],
        "name": "retrieveMessage",
        "outputs": [
            {
                "internalType": "string",
                "name": "",
                "type": "string"
            }
        ],
        "stateMutability": "view",
        "type": "function"
    },
    {
        "inputs": [
            {
                "internalType": "string",
                "name": "_content",
                "type": "string"
            },
            {
                "internalType": "string",
                "name": "_ensRecipient",
                "type": "string"
            },
            {
                "internalType": "uint256",
                "name": "_lockDuration",
                "type": "uint256"
            }
        ],
        "name": "storeMessage",
        "outputs": [
            {
                "internalType": "bytes32",
                "name": "",
                "type": "bytes32"
            }
        ],
        "stateMutability": "nonpayable",
        "type": "function"
    },
    {
        "inputs": [
            {
                "internalType": "address",
                "name": "newOwner",
                "type": "address"
            }
        ],
        "name": "transferOwnership",
        "outputs": [],
        "stateMutability": "nonpayable",
        "type": "function"
    }
]